baggingrnet
