Metadata-Version: 2.1
Name: baggingrnet
Version: 0.0.10
Summary: Library of Bagging of Deep Residual Neural Networks
Home-page: UNKNOWN
Author: Lianfa Li
Author-email: lspatial@gmail.com
License: UNKNOWN
Platform: UNKNOWN
